<?xml version="1.0" encoding="UTF-8"?>
<idList
	xmlns:xsi="http://www.w3.org/2001/XMLSchema-instance"
	xmlns="https://raw.githubusercontent.com/EDIandXML/OBOE/main/EDIRules.xsd">
	<idCode>3M <idValue>Quarter</idValue>
	</idCode>
	<idCode>6M <idValue>Half-year</idValue>
	</idCode>
	<idCode>AA <idValue>Air hour</idValue>
	</idCode>
	<idCode>AD <idValue>Air day</idValue>
	</idCode>
	<idCode>CD <idValue>Calendar day (includes weekends and holidays)</idValue>
	</idCode>
	<idCode>CW <idValue>Calendar week (7day)</idValue>
	</idCode>
	<idCode>D <idValue>Day</idValue>
	</idCode>
	<idCode>DC <idValue>Ten days period</idValue>
	</idCode>
	<idCode>DW <idValue>Work day</idValue>
	</idCode>
	<idCode>F <idValue>Period of two weeks</idValue>
	</idCode>
	<idCode>H <idValue>Hour</idValue>
	</idCode>
	<idCode>HM <idValue>Half month</idValue>
	</idCode>
	<idCode>M <idValue>Month</idValue>
	</idCode>
	<idCode>MN <idValue>Minute</idValue>
	</idCode>
	<idCode>P <idValue>Four month period</idValue>
	</idCode>
	<idCode>S <idValue>Second</idValue>
	</idCode>
	<idCode>SD <idValue>Surface day</idValue>
	</idCode>
	<idCode>SI <idValue>Indefinite</idValue>
	</idCode>
	<idCode>W <idValue>Week</idValue>
	</idCode>
	<idCode>WD <idValue>Working days</idValue>
	</idCode>
	<idCode>WW <idValue>5 day work week</idValue>
	</idCode>
	<idCode>Y <idValue>Year</idValue>
	</idCode>
	<idCode>ZZZ <idValue>Mutually defined</idValue>
	</idCode>
</idList>
